{
  "dev": {
    "awscloudformation": {
      "AuthRoleName": "amplify-bench-dev-182839-authRole",
      "UnauthRoleArn": "arn:aws:iam::476067034071:role/amplify-bench-dev-182839-unauthRole",
      "AuthRoleArn": "arn:aws:iam::476067034071:role/amplify-bench-dev-182839-authRole",
      "Region": "ap-northeast-1",
      "DeploymentBucketName": "amplify-bench-dev-182839-deployment",
      "UnauthRoleName": "amplify-bench-dev-182839-unauthRole",
      "StackName": "amplify-bench-dev-182839",
      "StackId": "arn:aws:cloudformation:ap-northeast-1:476067034071:stack/amplify-bench-dev-182839/0e22ded0-ad3d-11ed-bafc-0e965449e67f",
      "AmplifyAppId": "d2q6e9p7uodwqk"
    },
    "categories": {
      "auth": {
        "benchc59cf919": {
          "userPoolId": "ap-northeast-1_M9KvEx2KQ",
          "userPoolName": "Calendar",
          "webClientId": "5q0n61hrag8gv0it016rlo42hk",
          "nativeClientId": "5q0n61hrag8gv0it016rlo42hk"
        }
      }
    }
  }
}